{
  "nodes": {
    "0": {
      "id": "0",
      "injection": 45.45150874706263,
      "x": 168.15946826668088,
      "y": 229.38596288005095
    },
    "1": {
      "id": "1",
      "injection": 42.08676052477383,
      "x": 172.19665184129082,
      "y": 105.51381610610197
    },
    "2": {
      "id": "2",
      "injection": -105.43444074809017,
      "x": 10.883275463574961,
      "y": 203.33428408663556
    },
    "3": {
      "id": "3",
      "injection": 42.914553151627324,
      "x": 97.35408652840401,
      "y": 25.456231705699025
    },
    "4": {
      "id": "4",
      "injection": 14.750244194618361,
      "x": 286.15648083447104,
      "y": 254.85576917853103
    },
    "5": {
      "id": "5",
      "injection": 45.032545433574,
      "x": 276.71948464716735,
      "y": 68.28657689412944
    },
    "6": {
      "id": "6",
      "injection": 1.9324123443282981,
      "x": 100.56300561369821,
      "y": 161.71386087389436
    },
    "7": {
      "id": "7",
      "injection": -86.73358364789426,
      "x": 128.09550406908113,
      "y": 338.7801876621105
    },
    "3b": {
      "id": "3b",
      "injection": 0.0,
      "x": 97.35408652840401,
      "y": 25.456231705699025
    }
  },
  "lines": {
    "L0-1": {
      "id": "L0-1",
      "from_node": "0",
      "to_node": "1",
      "flow": -23.311915251113984,
      "limit": 50.0
    },
    "L0-2": {
      "id": "L0-2",
      "from_node": "0",
      "to_node": "2",
      "flow": 30.908222094817205,
      "limit": 50.0
    },
    "L0-4": {
      "id": "L0-4",
      "from_node": "0",
      "to_node": "4",
      "flow": -2.435023633002057,
      "limit": 50.0
    },
    "L0-6": {
      "id": "L0-6",
      "from_node": "0",
      "to_node": "6",
      "flow": 1.8879648331249743,
      "limit": 50.0
    },
    "L0-7": {
      "id": "L0-7",
      "from_node": "0",
      "to_node": "7",
      "flow": 38.40226070323647,
      "limit": 50.0
    },
    "L1-3": {
      "id": "L1-3",
      "from_node": "1",
      "to_node": "3",
      "flow": 1.2201373459311888,
      "limit": 50.0
    },
    "L1-5": {
      "id": "L1-5",
      "from_node": "1",
      "to_node": "5",
      "flow": -7.645172156510299,
      "limit": 50.0
    },
    "L1-6": {
      "id": "L1-6",
      "from_node": "1",
      "to_node": "6",
      "flow": 25.19988008423896,
      "limit": 50.0
    },
    "L2-6": {
      "id": "L2-6",
      "from_node": "2",
      "to_node": "6",
      "flow": -29.02025726169223,
      "limit": 50.0
    },
    "L2-7": {
      "id": "L2-7",
      "from_node": "2",
      "to_node": "7",
      "flow": 7.494038608419267,
      "limit": 50.0
    },
    "L4-5": {
      "id": "L4-5",
      "from_node": "4",
      "to_node": "5",
      "flow": -28.522063774622225,
      "limit": 50.0
    },
    "L4-7": {
      "id": "L4-7",
      "from_node": "4",
      "to_node": "7",
      "flow": 40.837284336238525,
      "limit": 50.0
    },
    "L2-3": {
      "id": "L2-3",
      "from_node": "2",
      "to_node": "3",
      "flow": 0.0,
      "limit": 50.0
    },
    "L3b-5": {
      "id": "L3b-5",
      "from_node": "3b",
      "to_node": "5",
      "flow": 0.0,
      "limit": 50.0
    }
  },
  "cost": 3.0
}